dataflow/__init__.py
dataflow/reader.py
pbi_dataflow_reader-0.1.3.dist-info/LICENSE
pbi_dataflow_reader-0.1.3.dist-info/METADATA
pbi_dataflow_reader-0.1.3.dist-info/WHEEL
pbi_dataflow_reader-0.1.3.dist-info/top_level.txt
pbi_dataflow_reader-0.1.3.dist-info/RECORD
