Metadata-Version: 2.1
Name: pbi-dataflow-reader
Version: 0.1.3
Summary: Python client library to access data from PowerBI dataflow
Home-page: https://github.com/allenwux/powerbi-datasource
Author: Xiaochen Wu
Author-email: xiwu@microsoft.com
License: MIT
Platform: UNKNOWN
Classifier: License :: OSI Approved :: MIT License
Classifier: Programming Language :: Python :: 3
Classifier: Programming Language :: Python :: 3.7
Requires-Dist: azure-storage-blob (<12.0.0)
Requires-Dist: pandas
